m9s_trytond-7.0.43.data/scripts/trytond
m9s_trytond-7.0.43.data/scripts/trytond-admin
m9s_trytond-7.0.43.data/scripts/trytond-console
m9s_trytond-7.0.43.data/scripts/trytond-cron
m9s_trytond-7.0.43.data/scripts/trytond-stat
m9s_trytond-7.0.43.data/scripts/trytond-worker
m9s_trytond-7.0.43.dist-info/licenses/LICENSE
trytond/__init__.py
trytond/admin.py
trytond/application.py
trytond/bus.py
trytond/cache.py
trytond/cache_redis.py
trytond/cache_serializer.py
trytond/commandline.py
trytond/config.py
trytond/console.py
trytond/const.py
trytond/convert.py
trytond/cron.py
trytond/exceptions.py
trytond/filestore.py
trytond/i18n.py
trytond/pool.py
trytond/pyson.py
trytond/rpc.py
trytond/security.py
trytond/sendmail.py
trytond/status.py
trytond/transaction.py
trytond/tryton.rnc
trytond/tryton.rng
trytond/url.py
trytond/worker.py
trytond/wsgi.py
trytond/backend/__init__.py
trytond/backend/database.py
trytond/backend/table.py
trytond/backend/postgresql/__init__.py
trytond/backend/postgresql/database.py
trytond/backend/postgresql/init.sql
trytond/backend/postgresql/table.py
trytond/backend/sqlite/__init__.py
trytond/backend/sqlite/database.py
trytond/backend/sqlite/init.sql
trytond/backend/sqlite/table.py
trytond/ir/__init__.py
trytond/ir/action.py
trytond/ir/action.xml
trytond/ir/attachment.py
trytond/ir/attachment.xml
trytond/ir/avatar.py
trytond/ir/cache.py
trytond/ir/calendar_.py
trytond/ir/calendar_.xml
trytond/ir/configuration.py
trytond/ir/cron.py
trytond/ir/cron.xml
trytond/ir/date.py
trytond/ir/email.xml
trytond/ir/email_.py
trytond/ir/error.py
trytond/ir/error.xml
trytond/ir/exceptions.py
trytond/ir/export.py
trytond/ir/export.xml
trytond/ir/ir.xml
trytond/ir/lang.py
trytond/ir/lang.xml
trytond/ir/message.py
trytond/ir/message.xml
trytond/ir/model.py
trytond/ir/model.xml
trytond/ir/module.py
trytond/ir/module.xml
trytond/ir/note.py
trytond/ir/note.xml
trytond/ir/queue.xml
trytond/ir/queue_.py
trytond/ir/resource.py
trytond/ir/routes.py
trytond/ir/rule.py
trytond/ir/rule.xml
trytond/ir/sequence.py
m9s_trytond-7.0.43.dist-info/METADATA
m9s_trytond-7.0.43.dist-info/WHEEL
m9s_trytond-7.0.43.dist-info/top_level.txt
m9s_trytond-7.0.43.dist-info/RECORD
